GPTCostCalculator/__init__.py
GPTCostCalculator/calculator.py
GPTCostCalculator-1.0.2.dist-info/LICENCE
GPTCostCalculator-1.0.2.dist-info/METADATA
GPTCostCalculator-1.0.2.dist-info/WHEEL
GPTCostCalculator-1.0.2.dist-info/top_level.txt
GPTCostCalculator-1.0.2.dist-info/RECORD
