Metadata-Version: 2.1
Name: GPTCostCalculator
Version: 1.0.2
Summary: Tool for estimating the cost of using different OpenAI API models
Home-page: https://github.com/GregoireAMATO/GPTCostCalculator
Author: Grégoire AMATO
Author-email: amato.gregoire@gmail.com
License-File: LICENCE
Requires-Dist: tiktoken
